leather/__init__.py
leather/axis.py
leather/chart.py
leather/data_types.py
leather/grid.py
leather/lattice.py
leather/svg.py
leather/testcase.py
leather/theme.py
leather/utils.py
leather/scales/__init__.py
leather/scales/base.py
leather/scales/linear.py
leather/scales/ordinal.py
leather/scales/temporal.py
leather/series/__init__.py
leather/series/base.py
leather/series/category.py
leather/shapes/__init__.py
leather/shapes/bars.py
leather/shapes/base.py
leather/shapes/columns.py
leather/shapes/dots.py
leather/shapes/line.py
leather/ticks/__init__.py
leather/ticks/base.py
leather/ticks/score.py
leather/ticks/score_time.py
leather-0.3.4.dist-info/COPYING
leather-0.3.4.dist-info/METADATA
leather-0.3.4.dist-info/WHEEL
leather-0.3.4.dist-info/top_level.txt
leather-0.3.4.dist-info/RECORD
